{
    "vodPic": "https://x.imgs.ovh/x/2023/09/05/64f680bb030b4.png",
    "drives": [
        {
            "name": "小羊login254",
            "server": "http://192.168.31.254:5244",
            "login": {
                "username": "admin",
                "password": "Wmz1021!!"
            }
        },
        {
            "name": "小羊",
            "server": "http://192.168.31.1:5244"
        },
        {
            "name": "小羊login",
            "server": "http://192.168.31.1:5244",
            "login": {
                "username": "admin",
                "password": "Wmz1021!!"
            }
        },
        {
            "name": "小羊2",
            "server": "http://192.168.31.2:5244"
        },
        {
            "name": "小羊login2",
            "server": "http://192.168.31.2:5244",
            "login": {
                "username": "admin",
                "password": "Wmz1021!!"
            }
        },
        {
            "name": "小雅",
            "server": "http://alist.xiaoya.pro"
        },
        {
            "name": "觸光",
            "server": "https://pan.ichuguang.com"
        },
        {
            "name": "一只魚",
            "server": "https://vtok.pp.ua"
        },
        {
            "name": "七米藍",
            "server": "https://al.chirmyram.com"
        },
        {
            "name": "神族九帝",
            "server": "https://alist.shenzjd.com"
        },
        {
            "name": "梓澪",
            "server": "https://zi0.cc"
        },
        {
            "name": "範本",
            "server": "https://one.fongmi.com",
            "search": true,
            "hidden": false,
            "login": {
                "username": "fongmi",
                "password": "fongmi"
            },
            "params": [
                {
                    "path": "/安齋拉拉",
                    "pass": "18181818"
                }
            ]
        }
    ]
}
